voicegen/__init__.py
voicegen/__main__.py
voicegen/voicegen.py
voicegen-0.1.1.dist-info/WHEEL
voicegen-0.1.1.dist-info/METADATA
voicegen-0.1.1.dist-info/RECORD
