Metadata-Version: 2.1
Name: voicegen
Version: 0.1.1
Summary: 
Author: Andrei Murashev
Author-email: muraigtor@gmail.com
Requires-Python: >=3.7,<4.0
Classifier: Programming Language :: Python :: 3
Classifier: Programming Language :: Python :: 3.7
Classifier: Programming Language :: Python :: 3.8
Classifier: Programming Language :: Python :: 3.9
Requires-Dist: pytils (==0.3)
Requires-Dist: requests (==2.25.1)
Requires-Dist: sox (==1.4.1)
